passutil/__init__.py
passutil/__main__.py
passutil/chars.py
passutil/pu.py
passutil-3.0.5.dist-info/LICENSE.txt
passutil-3.0.5.dist-info/METADATA
passutil-3.0.5.dist-info/WHEEL
passutil-3.0.5.dist-info/top_level.txt
passutil-3.0.5.dist-info/RECORD
