Metadata-Version: 2.1
Name: passutil
Version: 3.0.5
Summary: Cryptographically secure, easy-to-use, password generator
Home-page: https://github.com/aaronstanek/PythonPasswordUtility
Author: Aaron Stanek
Author-email: amr.stanek@gmail.com
License: UNKNOWN
Project-URL: Bug Tracker, https://github.com/aaronstanek/PythonPasswordUtility/issues
Platform: UNKNOWN
Classifier: Programming Language :: Python :: 3
Classifier: License :: OSI Approved :: MIT License
Classifier: Operating System :: OS Independent
Requires-Python: ~=3.6
License-File: LICENSE.txt
